{
    "unimi5":{
        "show":true,
        "name":"unimi5",
        "title":"MSc Computer Science - University of Milan, Italy",
        "link":"/",
        "date":"October 2022 - Present",
        "description":"",
        "tags":["University"],
        "expande": [""],
        "expandeText":"",
        "image:":""
    },
    "unimi3":{
        "show":true,
        "name":"unimi3",
        "title":"BSc Computer Science - University of Milan, Italy",
        "link":"/",
        "date":"October 2019 - October 2022",
        "description":"",
        "tags":["University"],
        "expande":["scient-vis","prog-dich","fisica","sicpriv","reti","swang","cg","stat","sisop","db","prog2","algo","logica","discreto","archi2","lfa","continuo","archi","prog"],
        "expandeText":"See all attended courses",
        "image:":""
    },
    "scient-vis":{
        "show":false,
        "name":"scient-vis",
        "title":"Scientific Visualization",
        "link":"/",
        "date":"Casiraghi Elena",
        "description":"",
        "tags":["Course"],
        "expande":[""],
        "expandeText":"",
        "image:":""
    },
    "prog-dich":{
        "show":false,
        "name":"prog-dich",
        "title":"Declarative Programming",
        "link":"/",
        "date":"Fiorentini Camillo, Momigliano Alberto Davide Adolfo",
        "description":"F# and Twelf",
        "tags":["Course"],
        "expande":[""],
        "expandeText":"",
        "image:":""
    },
    "fisica":{
        "show":false,
        "name":"fisica",
        "title":"Physics",
        "link":"/",
        "date":"Cosentino Lagomarsino Marco",
        "description":"",
        "tags":["Course"],
        "expande":[""],
        "expandeText":"",
        "image:":""
    },
    "sicpriv":{
        "show":false,
        "name":"sicpriv",
        "title":"Security and Privacy",
        "link":"/",
        "date":"Bruschi Danilo Mauro",
        "description":"",
        "tags":["Course"],
        "expande":[""],
        "expandeText":"",
        "image:":""
    },
    "reti":{
        "show":false,
        "name":"reti",
        "title":"Computer Networks",
        "link":"/",
        "date":"Gian Paolo Rossi",
        "description":"",
        "tags":["Course"],
        "expande":[""],
        "expandeText":"",
        "image:":""
    },
    "swang":{
        "show":false,
        "name":"swang",
        "title":"Software Engineering",
        "link":"/",
        "date":"Chiara Braghin, Elvinia Maria Riccobene",
        "description":"",
        "tags":["Course"],
        "expande":[""],
        "expandeText":"",
        "image:":""
    },
    "cg":{
        "show":false,
        "name":"cg",
        "title":"Computer Graphics",
        "link":"/",
        "date":"Marco Tarini",
        "description":"",
        "tags":["Course"],
        "expande":[""],
        "expandeText":"",
        "image:":""
    },
    "stat":{
        "show":false,
        "name":"stat",
        "title":"Statistics and Data Analysis",
        "link":"/",
        "date":"Dario Malchiodi",
        "description":"",
        "tags":["Course"],
        "expande":[""],
        "expandeText":"",
        "image:":""
    },
    "sisop":{
        "show":false,
        "name":"sisop",
        "title":"Operating Systems",
        "link":"/",
        "date":"Vincenzo Piuri",
        "description":"",
        "tags":["Course"],
        "expande":[""],
        "expandeText":"",
        "image:":""
    },
    "db":{
        "show":false,
        "name":"db",
        "title":"Databases",
        "link":"/",
        "date":"Ferrara Alfio",
        "description":"",
        "tags":["Course"],
        "expande":[""],
        "expandeText":"",
        "image:":""
    },
    "prog2":{
        "show":false,
        "name":"prog2",
        "title":"Programming II",
        "link":"/",
        "date":"Santini Massimo",
        "description":"",
        "tags":["Course"],
        "expande":[""],
        "expandeText":"",
        "image:":""
    },
    "algo":{
        "show":false,
        "name":"algo",
        "title":"Algorithms & Data Structures",
        "link":"/",
        "date":"Pighizzini Giovanni, Violetta Lonati",
        "description":"",
        "tags":["Course"],
        "expande":[""],
        "expandeText":"",
        "image:":""
    },
    "logica":{
        "show":false,
        "name":"logica",
        "title":"Mathematical Logic",
        "link":"/",
        "date":"Aguzzoli Stefano",
        "description":"",
        "tags":["Course"],
        "expande":[""],
        "expandeText":"",
        "image:":""
    },
    "discreto":{
        "show":false,
        "name":"discreto",
        "title":"Discrete Mathematics",
        "link":"/",
        "date":"Alice Garbagnati",
        "description":"",
        "tags":["Course"],
        "expande":[""],
        "expandeText":"",
        "image:":""
    },
    "archi2":{
        "show":false,
        "name":"archi2",
        "title":"Computer Architecture II",
        "link":"/",
        "date":"Nunzio Borghese, Matteo Re",
        "description":"",
        "tags":["Course"],
        "expande":[""],
        "expandeText":"",
        "image:":""
    },
    "lfa":{
        "show":false,
        "name":"lfa",
        "title":"Automata and Formal Languages",
        "link":"/",
        "date":"Beatrice Palano",
        "description":"",
        "tags":["Course"],
        "expande":[""],
        "expandeText":"",
        "image:":""
    },
    "continuo":{
        "show":false,
        "name":"continuo",
        "title":"Continuum Mathematics",
        "link":"/",
        "date":"Massimo Tarallo, Anna Gori",
        "description":"",
        "tags":["Course"],
        "expande":[""],
        "expandeText":"",
        "image:":""
    },
    "archi":{
        "show":false,
        "name":"archi",
        "title":"Computer Architecture I",
        "link":"/",
        "date":"Marco Tarini, Matteo Re",
        "description":"",
        "tags":["Course"],
        "expande":[""],
        "expandeText":"",
        "image:":""
    },
    "prog":{
        "show":false,
        "name":"prog",
        "title":"Programming I",
        "link":"/",
        "date":"Alberto Ceselli, Lorenzo Capra",
        "description":"",
        "tags":["Course"],
        "expande":[""],
        "expandeText":"",
        "image:":""
    },
    "lssvv":{
        "show":true,
        "name":"lssvv",
        "title":"Scientific High School \"Vittorio Veneto\", Milan, Italy",
        "link":"/",
        "date":"September 2014 - June 2019",
        "description":"",
        "tags":["High School"],
        "expande": [""],
        "expandeText":"",
        "image:":""
    },
    "fce":{
        "show":true,
        "name":"fce",
        "title":"First Cambridge English (FCE)",
        "link":"/",
        "date":"12 May 2018 @ British Council",
        "description":"",
        "tags":["Certificate"],
        "expande": [""],
        "expandeText":"",
        "image:":""
    }
}
